bezier_editor/__init__.py
bezier_editor/app.py
bezier_editor/cli.py
bezier_editor/streamlit_app.py
bezier_editor/core/__init__.py
bezier_editor/core/bezier.py
bezier_editor/core/presets.py
bezier_editor/io/__init__.py
bezier_editor/io/file_operations.py
bezier_editor/ui/__init__.py
bezier_editor/ui/main_view.py
bezier_editor/ui/sidebar.py
bezier_editor-0.1.1.post1.dist-info/licenses/LICENSE
tests/__init__.py
tests/test_bezier.py
tests/test_io.py
bezier_editor-0.1.1.post1.dist-info/METADATA
bezier_editor-0.1.1.post1.dist-info/WHEEL
bezier_editor-0.1.1.post1.dist-info/entry_points.txt
bezier_editor-0.1.1.post1.dist-info/top_level.txt
bezier_editor-0.1.1.post1.dist-info/RECORD
