Metadata-Version: 2.4
Name: bezier-editor
Version: 0.1.1.post1
Summary: Interactive Bezier Curve Editor with Streamlit
Home-page: https://github.com/laurent-brisson/bezier-editor
Author: Laurent Brisson
Author-email: laurent.brisson@imt-atlantique.fr
Classifier: Programming Language :: Python :: 3
Classifier: License :: OSI Approved :: MIT License
Classifier: Operating System :: OS Independent
Requires-Python: >=3.7
License-File: LICENSE
Requires-Dist: streamlit>=1.15.0
Requires-Dist: numpy>=1.20.0
Requires-Dist: matplotlib>=3.4.0
Requires-Dist: pandas>=1.3.0
Dynamic: author
Dynamic: author-email
Dynamic: classifier
Dynamic: description
Dynamic: description-content-type
Dynamic: home-page
Dynamic: license-file
Dynamic: requires-dist
Dynamic: requires-python
Dynamic: summary
